defillama/__init__.py
defillama/__version__.py
defillama/_utils.py
defillama/abi_decoder.py
defillama/bridges.py
defillama/coins.py
defillama/fees_revenue.py
defillama/stablecoins.py
defillama/tvl.py
defillama/volumes.py
defillama/yields.py
DeFiLlama_Curl-2.0.1.dist-info/LICENSE
DeFiLlama_Curl-2.0.1.dist-info/METADATA
DeFiLlama_Curl-2.0.1.dist-info/WHEEL
DeFiLlama_Curl-2.0.1.dist-info/top_level.txt
DeFiLlama_Curl-2.0.1.dist-info/RECORD
