Metadata-Version: 2.1
Name: DeFiLlama-Curl
Version: 2.0.1
Summary: Unofficial Python wrapper for DeFi Llama API client using the PyCurl module.
Home-page: https://github.com/the-praxs/DeFiLlama
Author: Pratyush Shukla
Author-email: ps4534@nyu.edu
License: Apache License 2.0
Platform: UNKNOWN
Classifier: Programming Language :: Python :: 3.6
Classifier: Programming Language :: Python :: 3.7
Classifier: Programming Language :: Python :: 3.8
Classifier: Programming Language :: Python :: 3.9
Classifier: Programming Language :: Python :: 3.10
Classifier: License :: OSI Approved :: Apache Software License
Classifier: Operating System :: OS Independent
Requires-Python: >3.6
License-File: LICENSE
Requires-Dist: pycurl (>=7.44.1)
